connery/__init__.py
connery-0.0.0.dist-info/METADATA
connery-0.0.0.dist-info/WHEEL
connery-0.0.0.dist-info/top_level.txt
connery-0.0.0.dist-info/RECORD
