Metadata-Version: 2.1
Name: connery
Version: 0.0.0
Summary: Coming soon
Author-email: Connery <contact@connery.io>
